[{"description": "Dualer Student im Bereich Hotel- und Tourismusmanagement m/w/d", "location": [{"address": {"addressCountry": "DE", "addressLocality": "Karlsruhe, Baden", "addressRegion": "Baden-W\u00fcrttemberg", "postalCode": "76227", "streetAddress": ""}, "geo": {"latitude": 48.9905168, "longitude": 8.4738251}}], "additionalType": ["http://w3id.org/openeduhub/vocabs/locationType/D2eb8b66-7a56-4210-9f99-195fea13fe3b"], "name": "Hotel Der Blaue Reiter GmbH & Co. KG", "url": "https://www.arbeitsagentur.de/jobsuche/jobdetail/12518-ECWKZM-S"}, {"description": "Dualer Student m/w/d - BWL Freizeitwirtschaft", "location": [{"address": {"addressCountry": "DE", "addressLocality": "F\u00fcssen", "addressRegion": "Bayern", "postalCode": "87629", "streetAddress": ""}, "geo": {"latitude": 47.5834401, "longitude": 10.6653462}}], "additionalType": ["http://w3id.org/openeduhub/vocabs/locationType/D2eb8b66-7a56-4210-9f99-195fea13fe3b"], "name": "Hotel Sommer", "url": "https://www.arbeitsagentur.de/jobsuche/jobdetail/12518-CI2YQC-S"}, {"description": "Dualer Student Hotel- und Tourismus Management m/w/d", "location": [{"address": {"addressCountry": "DE", "addressLocality": "Berlin", "addressRegion": "Berlin", "postalCode": "10785", "streetAddress": ""}, "geo": {"latitude": 52.5063269, "longitude": 13.3650884}}], "additionalType": ["http://w3id.org/openeduhub/vocabs/locationType/D2eb8b66-7a56-4210-9f99-195fea13fe3b"], "name": "JW MARRIOTT BERLIN", "url": "https://www.arbeitsagentur.de/jobsuche/jobdetail/12518-ZPGGTZ-S"}, {"description": "Dualer Student (m/w/d) Hotelmanagement", "location": [{"address": {"addressCountry": "DE", "addressLocality": "Donaueschingen", "addressRegion": "Baden-W\u00fcrttemberg", "postalCode": "78166", "streetAddress": ""}, "geo": {"latitude": 47.9595031, "longitude": 8.4963576}}], "additionalType": ["http://w3id.org/openeduhub/vocabs/locationType/D2eb8b66-7a56-4210-9f99-195fea13fe3b"], "name": "DER \u00d6SCHBERGHOF", "url": "https://www.arbeitsagentur.de/jobsuche/jobdetail/12518-CN3EM6-S"}, {"description": "Auszubildende Duales System BA (m/w/d)", "location": [{"address": {"addressCountry": "DE", "addressLocality": "H\u00f6hr-Grenzhausen", "addressRegion": "Rheinland-Pfalz", "postalCode": "56203", "streetAddress": ""}, "geo": {"latitude": 50.4388502, "longitude": 7.6697195}}], "additionalType": ["http://w3id.org/openeduhub/vocabs/locationType/D2eb8b66-7a56-4210-9f99-195fea13fe3b"], "name": "Hotel ZUGBR\u00dcCKE Grenzau GmbH", "url": "https://www.arbeitsagentur.de/jobsuche/jobdetail/12518-LOLB3X-S"}, {"description": "Dualer Student m/w/d Tourismuswirtschaft", "location": [{"address": {"addressCountry": "DE", "addressLocality": "Sylt", "addressRegion": "Schleswig-Holstein", "postalCode": "25980", "streetAddress": ""}, "geo": {"latitude": 54.8778881, "longitude": 8.3690889}}], "additionalType": ["http://w3id.org/openeduhub/vocabs/locationType/D2eb8b66-7a56-4210-9f99-195fea13fe3b"], "name": "LONG ISLAND HOUSE SYLT - SYLT HOTEL", "url": "https://www.arbeitsagentur.de/jobsuche/jobdetail/12518-ZGTH7Q-S"}, {"description": "Dualer Student m/w/d Betriebswirtschaft (B.A.)", "location": [{"address": {"addressCountry": "DE", "addressLocality": "Juist", "addressRegion": "Niedersachsen", "postalCode": "26571", "streetAddress": ""}, "geo": {"latitude": 53.6761581, "longitude": 6.9820501}}], "additionalType": ["http://w3id.org/openeduhub/vocabs/locationType/D2eb8b66-7a56-4210-9f99-195fea13fe3b"], "name": "Romantik Hotel Achterdiek", "url": "https://www.arbeitsagentur.de/jobsuche/jobdetail/12518-CQ52Q5-S"}, {"description": "Ausbildung zum Hotel- / Gastgewerbeassistent (m/w/d)", "location": [{"address": {"addressCountry": "AT", "addressLocality": "", "addressRegion": "", "postalCode": "", "streetAddress": ""}, "geo": {"latitude": 0.0, "longitude": 0.0}}], "additionalType": ["http://w3id.org/openeduhub/vocabs/locationType/D2eb8b66-7a56-4210-9f99-195fea13fe3b"], "name": "Hotel Singer OG", "url": "https://www.arbeitsagentur.de/jobsuche/jobdetail/11858-6087993-STA-S"}, {"description": "Duales Studium im Bereich Tourismus- und Hotelmanagement (m/w/d) - Ausbildung 2024", "location": [{"address": {"addressCountry": "DE", "addressLocality": "Bad Zwischenahn", "addressRegion": "Niedersachsen", "postalCode": "26160", "streetAddress": "Eiden 9"}, "geo": {"latitude": 53.1888019, "longitude": 8.0326627}}], "additionalType": ["http://w3id.org/openeduhub/vocabs/locationType/D2eb8b66-7a56-4210-9f99-195fea13fe3b"], "name": "Jagdhaus Eiden GmbH", "url": "https://www.arbeitsagentur.de/jobsuche/jobdetail/10000-1194701654-S"}, {"description": "Duales Studium im Bereich Tourismus- und Hotelmanagement (m/w/d) - Ausbildung 2023", "location": [{"address": {"addressCountry": "DE", "addressLocality": "Bad Zwischenahn", "addressRegion": "Niedersachsen", "postalCode": "26160", "streetAddress": "Eiden 9"}, "geo": {"latitude": 53.1888019, "longitude": 8.0326627}}], "additionalType": ["http://w3id.org/openeduhub/vocabs/locationType/D2eb8b66-7a56-4210-9f99-195fea13fe3b"], "name": "Jagdhaus Eiden GmbH", "url": "https://www.arbeitsagentur.de/jobsuche/jobdetail/10000-1189102313-S"}]